GitAutoVersion/GitAutoVersion.py
GitAutoVersion/__init__.py
GitAutoVersion/test.py
GitAutoVersion-0.0.12.dev0.dist-info/LICENSE
GitAutoVersion-0.0.12.dev0.dist-info/METADATA
GitAutoVersion-0.0.12.dev0.dist-info/WHEEL
GitAutoVersion-0.0.12.dev0.dist-info/top_level.txt
GitAutoVersion-0.0.12.dev0.dist-info/RECORD
