Metadata-Version: 2.1
Name: GitAutoVersion
Version: 0.0.12.dev0
Summary: Get a descriptive version string in a git repository.
Home-page: https://gitlab.com/3134/GitAutoProject
Author: Sebastian GABRIEL
Author-email: dev@3134.at
License: UNKNOWN
Project-URL: Bug Tracker, https://gitlab.com/3134/GitAutoProject/-/issues
Project-URL: Source, https://gitlab.com/3134/GitAutoProject/
Platform: UNKNOWN
Classifier: Programming Language :: Python :: 3
Classifier: License :: OSI Approved :: MIT License
Classifier: Operating System :: OS Independent
Requires-Python: >=3.6
License-File: LICENSE
